{
  "header": {
    "title": "Conference Proceedings",
    "description": "Access the official compilation of peer-reviewed papers presented at the conference. The proceedings highlight significant research contributions across all tracks and are published in accordance with IEEE standards."
  },
  "archive": {
    "title": "Access Conference Proceedings of IC-SAGAR 2026",
    "description": "Access the complete collection of research papers and presentations from IC-SAGAR 2026",
    "coverImage": "https://placehold.co/400x550/1a1a1a/FFF?text=Proceedings+Cover",
    "items": [
      {
        "title": "Conference Proceedings @ Springer Nature",
        "description": "All papers are indexed in Springer Nature",
        "buttonText": "Explore",
        "link": "https://www.springernature.com/",
        "icon": "FaGlobe",
        "isExternal": true
      },
      {
        "title": "Conference Souvenir",
        "description": "Coming Soon",
        "buttonText": "Coming Soon",
        "link": "#",
        "icon": "FaFilePdf",
        "isDownload": false
      }
    ]
  }
}